cardiac_geometries_core/__init__.py
cardiac_geometries_core/__main__.py
cardiac_geometries_core/biv_ellipsoid.py
cardiac_geometries_core/cli.py
cardiac_geometries_core/cylinder.py
cardiac_geometries_core/lv_ellipsoid.py
cardiac_geometries_core/slab.py
cardiac_geometries_core/utils.py
cardiac_geometries_core-1.2.2.dist-info/licenses/LICENSE
cardiac_geometries_core-1.2.2.dist-info/METADATA
cardiac_geometries_core-1.2.2.dist-info/WHEEL
cardiac_geometries_core-1.2.2.dist-info/entry_points.txt
cardiac_geometries_core-1.2.2.dist-info/top_level.txt
cardiac_geometries_core-1.2.2.dist-info/RECORD
